long_to_short_cli/__init__.py
long_to_short_cli/long_to_short_cli.py
long_to_short_cli-1.1.0.dist-info/LICENSE
long_to_short_cli-1.1.0.dist-info/METADATA
long_to_short_cli-1.1.0.dist-info/WHEEL
long_to_short_cli-1.1.0.dist-info/entry_points.txt
long_to_short_cli-1.1.0.dist-info/top_level.txt
long_to_short_cli-1.1.0.dist-info/RECORD
